webscrapingapi/__init__.py
webscrapingapi/client.py
webscrapingapi-1.2.6.dist-info/LICENSE.txt
webscrapingapi-1.2.6.dist-info/METADATA
webscrapingapi-1.2.6.dist-info/WHEEL
webscrapingapi-1.2.6.dist-info/top_level.txt
webscrapingapi-1.2.6.dist-info/RECORD
