Metadata-Version: 2.1
Name: webscrapingapi
Version: 1.2.6
Summary: WebScrapingApi Python SDK
Home-page: https://github.com/WebScrapingAPI/python-sdk
Author: Sorin-Gabriel Marica
Author-email: sorin.marica@jeco.dev
Maintainer: webscrapingapi
Maintainer-email: account@jeco.dev
License: MIT
Platform: UNKNOWN
Classifier: License :: OSI Approved :: MIT License
Classifier: Programming Language :: Python
Classifier: Programming Language :: Python :: 3
Classifier: Programming Language :: Python :: 3.6
Classifier: Programming Language :: Python :: 3.7
Classifier: Programming Language :: Python :: 3.8
Classifier: Topic :: Software Development :: Libraries :: Python Modules
Requires-Python: >=3.6
License-File: LICENSE.txt
Requires-Dist: requests
